{
  "title": "LaRobe Storefront",
  "titleTemplate": "%s - LaRobe Storefront",
  "description": "dimitrmichel.com",
  "openGraph": {
    "title": "LaRobe Storefront",
    "description": "LaRobe Storefront - https://www.dimitrimichel.com/larobe",
    "type": "website",
    "locale": "en_IE",
    "url": "https://dimitrimichel.com/larobe",
    "site_name": "LaRobe",
    "images": [
      {
        "url": "/card.png",
        "width": 800,
        "height": 600,
        "alt": "La Robe logo"
      }
    ]
  },
  "twitter": {
    "handle": "@",
    "site": "@",
    "cardType": "summary_large_image"
  }
}
